[
  {
    "id": 1,
    "name": "Livia Helen",
    "username": "liviahelen",
    "postedAt": "2021-07-01T12:00:00",
    "content": "Lorem ipsum dolor sit amet consectetur adipisicing elit. Magnam id, totam, quas ratione deleniti ea voluptas et numquam consequatur eligendi aliquam illum laudantium distinctio atque non, eius fugit cumque est.",
    "photo_url": "https://avatars.githubusercontent.com/u/62712621?v=4"
  },
  {
    "id": 2,
    "name": "Jhon Doe",
    "username": "jhondoe",
    "postedAt": "2023-12-01T12:00:00",
    "content": "Proin a est nec ligula tincidunt auctor sit amet ac magna. Vivamus cursus lobortis turpis, quis scelerisque metus hendrerit ut. Duis et mauris eu ante scelerisque ullamcorper sit amet id enim. Sed lacinia augue id velit sagittis egestas. Aliquam eget gravida dui, nec cursus sem. Mauris in tincidunt purus, a interdum elit. Proin tempor volutpat diam dictum porta. Proin velit mi, sollicitudin dictum dignissim vitae, facilisis vel lorem. Quisque porttitor pretium libero, id tristique mi iaculis vulputate. Nullam dolor sapien, commodo a laoreet non, hendrerit vel ante. Etiam eu efficitur enim. Sed tempor non orci nec rutrum. Vestibulum convallis feugiat lorem vel tempor. Maecenas non hendrerit nisi, ac aliquet dolor.",
    "photo_url": "https://avatars.githubusercontent.com/u/62712621?v=4"
  }
]